bqup/__init__.py
bqup/dataset.py
bqup/main.py
bqup/project.py
bqup/routine.py
bqup/table.py
bqup_spartez-0.0.7.dist-info/LICENSE
bqup_spartez-0.0.7.dist-info/METADATA
bqup_spartez-0.0.7.dist-info/WHEEL
bqup_spartez-0.0.7.dist-info/entry_points.txt
bqup_spartez-0.0.7.dist-info/top_level.txt
bqup_spartez-0.0.7.dist-info/RECORD
