Metadata-Version: 2.1
Name: bqup-spartez
Version: 0.0.7
Summary: BigQuery backup scripts - Spartez fork
Home-page: https://github.com/spartez/bqup
Author: Thinking Machines Data Science && Spartez-software
Author-email: bartlomiej.zieba@spartez-software.com
License: MIT License
Keywords: google bigquery,bigquery,bq,backup,bqup,spartez
Platform: UNKNOWN
Requires-Dist: docopt
Requires-Dist: google-cloud-bigquery (==1.24.0)
